{
  "_comment": "Mapping OSM tags → hint stringa per Spendif.AI. Usato da build_static_rules.py.",
  "shop=supermarket":      {"hint": "Alimentari > Spesa supermercato"},
  "shop=convenience":      {"hint": "Alimentari > Spesa di prossimità"},
  "shop=bakery":           {"hint": "Alimentari > Panetteria"},
  "shop=butcher":          {"hint": "Alimentari > Macelleria"},
  "shop=greengrocer":      {"hint": "Alimentari > Frutta e verdura"},
  "shop=alcohol":          {"hint": "Alimentari > Bevande e alcolici"},
  "amenity=fuel":          {"hint": "Trasporti > Carburante"},
  "amenity=fast_food":     {"hint": "Svago e tempo libero > Ristoranti e bar"},
  "amenity=restaurant":    {"hint": "Svago e tempo libero > Ristoranti e bar"},
  "amenity=cafe":          {"hint": "Svago e tempo libero > Bar e caffè"},
  "amenity=bar":           {"hint": "Svago e tempo libero > Bar e caffè"},
  "amenity=pub":           {"hint": "Svago e tempo libero > Bar e caffè"},
  "amenity=pharmacy":      {"hint": "Salute > Farmaci"},
  "amenity=bank":          {"hint": "Finanza e assicurazioni > Servizi bancari"},
  "amenity=atm":           {"hint": "Finanza e assicurazioni > Prelievo contante"},
  "amenity=cinema":        {"hint": "Svago e tempo libero > Cinema e teatro"},
  "amenity=theatre":       {"hint": "Svago e tempo libero > Cinema e teatro"},
  "amenity=gym":           {"hint": "Salute > Sport e palestra"},
  "amenity=parking":       {"hint": "Trasporti > Parcheggio"},
  "amenity=car_wash":      {"hint": "Trasporti > Autolavaggio"},
  "amenity=post_office":   {"hint": "Casa > Posta e spedizioni"},
  "amenity=hospital":      {"hint": "Salute > Visite mediche"},
  "amenity=clinic":        {"hint": "Salute > Visite mediche"},
  "amenity=dentist":       {"hint": "Salute > Dentista"},
  "amenity=veterinary":    {"hint": "Svago e tempo libero > Animali domestici"},
  "shop=clothing":         {"hint": "Abbigliamento > Abbigliamento"},
  "shop=shoes":            {"hint": "Abbigliamento > Scarpe"},
  "shop=electronics":      {"hint": "Tecnologia > Elettronica"},
  "shop=computer":         {"hint": "Tecnologia > Computer"},
  "shop=mobile_phone":     {"hint": "Tecnologia > Telefonia"},
  "shop=furniture":        {"hint": "Casa > Arredamento"},
  "shop=hardware":         {"hint": "Casa > Ferramenta"},
  "shop=doityourself":     {"hint": "Casa > Ferramenta"},
  "shop=sports":           {"hint": "Salute > Sport e palestra"},
  "shop=books":            {"hint": "Svago e tempo libero > Libri e musica"},
  "shop=stationery":       {"hint": "Istruzione > Cancelleria"},
  "shop=chemist":          {"hint": "Salute > Cosmetici e cura persona"},
  "shop=optician":         {"hint": "Salute > Ottica"},
  "shop=jewelry":          {"hint": "Abbigliamento > Gioielleria"},
  "shop=cosmetics":        {"hint": "Salute > Cosmetici e cura persona"},
  "shop=pet":              {"hint": "Svago e tempo libero > Animali domestici"},
  "shop=florist":          {"hint": "Casa > Fiori e piante"},
  "shop=gift":             {"hint": "Svago e tempo libero > Regali"},
  "leisure=fitness_centre":{"hint": "Salute > Sport e palestra"},
  "leisure=sports_centre": {"hint": "Salute > Sport e palestra"},
  "leisure=golf_course":   {"hint": "Svago e tempo libero > Sport"},
  "office=insurance":      {"hint": "Finanza e assicurazioni > Assicurazioni"},
  "office=financial":      {"hint": "Finanza e assicurazioni > Servizi finanziari"},
  "office=travel_agent":   {"hint": "Svago e tempo libero > Viaggi e vacanze"},
  "tourism=hotel":         {"hint": "Svago e tempo libero > Alloggio"},
  "tourism=hostel":        {"hint": "Svago e tempo libero > Alloggio"},
  "tourism=motel":         {"hint": "Svago e tempo libero > Alloggio"}
}
